LICENSE
README.md
setup.py
ipamd/__init__.py
ipamd.egg-info/PKG-INFO
ipamd.egg-info/SOURCES.txt
ipamd.egg-info/dependency_links.txt
ipamd.egg-info/requires.txt
ipamd.egg-info/top_level.txt
ipamd/app/__init__.py
ipamd/app/analysis.py
ipamd/app/builder.py
ipamd/app/sakuanna.py
ipamd/app/simulation.py
ipamd/app/lib/galamost.so
ipamd/data/forcefield/Calvados1.xml
ipamd/data/forcefield/Calvados2.xml
ipamd/data/forcefield/Calvados3.xml
ipamd/data/forcefield/Calvados_lc.xml
ipamd/data/forcefield/HPS-Urry.xml
ipamd/data/forcefield/HPST.xml
ipamd/data/forcefield/Initial.xml
ipamd/data/forcefield/mpipi.xml
ipamd/plugins/analysis/data_process/distribution.py
ipamd/plugins/analysis/data_process/flatten.py
ipamd/plugins/analysis/data_process/merge.py
ipamd/plugins/analysis/data_process/normalize.py
ipamd/plugins/analysis/data_process/plot.py
ipamd/plugins/analysis/data_process/print.py
ipamd/plugins/analysis/data_process/save.py
ipamd/plugins/analysis/data_process/to_df.py
ipamd/plugins/analysis/operator/contact_map.py
ipamd/plugins/analysis/operator/contact_number.py
ipamd/plugins/analysis/operator/density.py
ipamd/plugins/analysis/operator/flory_monomer.py
ipamd/plugins/analysis/operator/flory_multimer.py
ipamd/plugins/analysis/operator/momentum.py
ipamd/plugins/analysis/operator/potential.py
ipamd/plugins/analysis/operator/rg.py
ipamd/plugins/analysis/operator/ripley.py
ipamd/plugins/analysis/operator/rmsd.py
ipamd/plugins/analysis/operator/rmsf.py
ipamd/plugins/analysis/operator/temperature.py
ipamd/plugins/builder/converter/align_center.py
ipamd/plugins/builder/converter/merge_nearest.py
ipamd/plugins/builder/converter/read_xml.py
ipamd/plugins/builder/converter/to_aa.py
ipamd/plugins/builder/converter/to_cif.py
ipamd/plugins/builder/converter/to_pdb.py
ipamd/plugins/builder/converter/to_xml.py
ipamd/plugins/builder/converter/unwrap.py
ipamd/plugins/builder/genbox/enneutral.py
ipamd/plugins/builder/genbox/place_molecule_at.py
ipamd/plugins/builder/genbox/place_molecule_periodically.py
ipamd/plugins/builder/genbox/place_molecule_randomly.py
ipamd/plugins/builder/genbox/sub_box.py
