Metadata-Version: 2.4
Name: ipamd
Version: 0.0.13
Summary: A Python package for MD simulations and analysis of biomolecules
Author: Xiaoyang Liu
Author-email: liuxiaoyang_Q@outlook.com
License: LGPL-3.0
Requires-Python: >=3.12
License-File: LICENSE
Requires-Dist: tabulate
Requires-Dist: rich
Requires-Dist: numba
Requires-Dist: matplotlib
Requires-Dist: biopython
Requires-Dist: requests
Requires-Dist: pandas
Requires-Dist: numpy
Requires-Dist: pybioseq
Dynamic: author
Dynamic: author-email
Dynamic: description
Dynamic: description-content-type
Dynamic: license
Dynamic: license-file
Dynamic: requires-dist
Dynamic: requires-python
Dynamic: summary
